LICENSE
MANIFEST.in
README.md
pyproject.toml
requirements.txt
setup.cfg
setup.py
statprly/__init__.py
statprly/constants.py
statprly/errors.py
statprly.egg-info/PKG-INFO
statprly.egg-info/SOURCES.txt
statprly.egg-info/dependency_links.txt
statprly.egg-info/requires.txt
statprly.egg-info/top_level.txt
statprly/mono_digits_recognizer/__init__.py
statprly/mono_digits_recognizer/data_reader.py
statprly/mono_digits_recognizer/interfaces.py
statprly/mono_digits_recognizer/recognizer.py
statprly/mono_digits_recognizer/digit_standards/digits.json
statprly/mono_digits_recognizer/standards_provider/__init__.py
statprly/mono_digits_recognizer/standards_provider/interfaces.py
statprly/mono_digits_recognizer/standards_provider/provider.py
statprly/optimal_drop_off_location_searcher/__init__.py
statprly/optimal_drop_off_location_searcher/interfaces.py
statprly/optimal_drop_off_location_searcher/location_searcher.py